MANIFEST.in
README.md
pyproject.toml
setup.py
amuse_ph4.egg-info/PKG-INFO
amuse_ph4.egg-info/SOURCES.txt
amuse_ph4.egg-info/dependency_links.txt
amuse_ph4.egg-info/requires.txt
amuse_ph4.egg-info/top_level.txt
src/amuse/community/ph4/Makefile
src/amuse/community/ph4/__init__.py
src/amuse/community/ph4/_version.py
src/amuse/community/ph4/binary_hist.py
src/amuse/community/ph4/interface.cc
src/amuse/community/ph4/interface.py
src/amuse/community/ph4/plot_energy_vs_t.py
src/amuse/community/ph4/plot_kT_vs_t.py
src/amuse/community/ph4/plotq.py
src/amuse/community/ph4/test_multiples.py
src/amuse/community/ph4/test_multiples2.py
src/amuse/community/ph4/test_ph4.py
src/amuse/community/ph4/test_sync.py
src/amuse/community/ph4/src/GPU_options.txt
src/amuse/community/ph4/src/Makefile
src/amuse/community/ph4/src/Makefile.ph4
src/amuse/community/ph4/src/README
src/amuse/community/ph4/src/TODO
src/amuse/community/ph4/src/analyze.cc
src/amuse/community/ph4/src/close_encounter.cc
src/amuse/community/ph4/src/ctest_nstab.cc
src/amuse/community/ph4/src/debug.cc
src/amuse/community/ph4/src/debug.h
src/amuse/community/ph4/src/diag.cc
src/amuse/community/ph4/src/f2c.c
src/amuse/community/ph4/src/f2c.h
src/amuse/community/ph4/src/ftest_nstab.f
src/amuse/community/ph4/src/gpu.cc
src/amuse/community/ph4/src/grape.cc
src/amuse/community/ph4/src/grape.h
src/amuse/community/ph4/src/hdyn.cc
src/amuse/community/ph4/src/hdyn.h
src/amuse/community/ph4/src/idata.cc
src/amuse/community/ph4/src/idata.h
src/amuse/community/ph4/src/jdata.cc
src/amuse/community/ph4/src/jdata.h
src/amuse/community/ph4/src/kepler.cc
src/amuse/community/ph4/src/kepler.h
src/amuse/community/ph4/src/nstab.c
src/amuse/community/ph4/src/nstab.f
src/amuse/community/ph4/src/nstab.h
src/amuse/community/ph4/src/old_close_encounter.cc
src/amuse/community/ph4/src/parallel_hermite_4.cc
src/amuse/community/ph4/src/plummer100.in
src/amuse/community/ph4/src/plummer16k.in
src/amuse/community/ph4/src/plummer1k.in
src/amuse/community/ph4/src/plummer4k.in
src/amuse/community/ph4/src/plummer8k.in
src/amuse/community/ph4/src/plummer_test.in
src/amuse/community/ph4/src/random_nstab.cc
